huscy/subject_consents/__init__.py
huscy/subject_consents/apps.py
huscy/subject_consents/models.py
huscy/subject_consents/migrations/0001_initial.py
huscy/subject_consents/migrations/__init__.py
huscy.subject_consents-0.1.0a0.dist-info/METADATA
huscy.subject_consents-0.1.0a0.dist-info/WHEEL
huscy.subject_consents-0.1.0a0.dist-info/top_level.txt
huscy.subject_consents-0.1.0a0.dist-info/RECORD
